<?xml version="1.0" encoding="UTF-8"?>
<soap:Envelope xmlns:xsd="http://www.w3.org/2001/XMLSchema" xmlns:xsi="http://www.w3.org/2001/XMLSchema-instance" xmlns:soap="http://schemas.xmlsoap.org/soap/envelope/">
  <soap:Body>
    <ReceivingTicketAddResponse xmlns="http://rex11.com/webmethods/">
      <ReceivingTicketAddResult>
        <Notifications>
          <Notification>
            <ErrorCode>12</ErrorCode>
            <Severity>DataNotValid</Severity>
            <Message>ReceivingTicket/SupplierDetails/Country is not valid</Message>
          </Notification>
          <Notification>
            <ErrorCode>32</ErrorCode>
            <Severity>DataNotValid</Severity>
            <Message>ReceivingTicket/Shipmentitemslist/Size[item 1] is not valid</Message>
          </Notification>
        </Notifications>
        <ReceivingTicketId/>
      </ReceivingTicketAddResult>
    </ReceivingTicketAddResponse>
  </soap:Body>
</soap:Envelope>